epik8spydev/__init__.py
epik8spydev/motor.py
epik8spydev/tml_motor.py
epik8spydev-0.1.0.dist-info/METADATA
epik8spydev-0.1.0.dist-info/WHEEL
epik8spydev-0.1.0.dist-info/top_level.txt
epik8spydev-0.1.0.dist-info/RECORD
