Metadata-Version: 2.1
Name: epik8spydev
Version: 0.1.0
Summary: A package for controlling motors,camera,magnets with EPICS and asyncio.
License: UNKNOWN
Platform: UNKNOWN
Classifier: Programming Language :: Python :: 3
Classifier: License :: OSI Approved :: MIT License
Classifier: Operating System :: OS Independent
Requires-Python: >=3.6
Requires-Dist: pyepics
Requires-Dist: asyncio
